docker_printer/__init__.py
docker_printer/__main__.py
docker_printer/cli.py
docker_printer/models.py
docker_printer/utils.py
docker_printer/resources/__init__.py
docker_printer/resources/templates/base.Dockerfile.jinja2
docker_printer/resources/templates/stage.Dockerfile.jinja2
docker_printer-1.0.0.dist-info/entry_points.txt
docker_printer-1.0.0.dist-info/WHEEL
docker_printer-1.0.0.dist-info/METADATA
docker_printer-1.0.0.dist-info/RECORD
