Metadata-Version: 2.1
Name: docker-printer
Version: 1.0.0
Summary: Composer for dockerfiles
Author-email: Rearc Data <data@rearc.io>
Requires-Python: >=3.7
Classifier: Programming Language :: Python :: 3
Classifier: License :: OSI Approved :: MIT License
Classifier: Operating System :: OS Independent
Requires-Dist: pyyaml
Requires-Dist: jinja2
Requires-Dist: click
Requires-Dist: pydantic==2.*
Requires-Dist: typer
Requires-Dist: rich
Project-URL: Bug Tracker, https://github.com/rearc-data/docker-printer/issues
Project-URL: Homepage, https://github.com/rearc-data/docker-printer
